sner/__init__.py
sner/classes/__init__.py
sner/classes/display.py
sner/classes/rule.py
sner/classes/token.py
sner/models/__init__.py
sner/models/ner.py
sner/models/sklearn_launcher.py
sner/scripts/__init__.py
sner/scripts/analysis.py
sner/scripts/context.py
sner/scripts/export.py
sner/scripts/export_atf.py
sner/scripts/formatting.py
sner/scripts/import_corpus.py
sner/scripts/names.py
sner/scripts/output.py
sner/scripts/overfit_check.py
sner/scripts/professions.py
sner/scripts/readnames.py
sner/scripts/spelling.py
sner/scripts/utilities.py
sner/scripts/ner/__init__.py
sner/scripts/ner/contextualfromnames.py
sner/scripts/ner/namesfromrule.py
sner/scripts/ner/rulefilter.py
sner/scripts/ner/rulesperformance.py
sner/scripts/ner/spellingfromnames.py
sner/scripts/ner/updatetokenstrength.py
sumerian_ner-0.1.1.dist-info/METADATA
sumerian_ner-0.1.1.dist-info/RECORD
sumerian_ner-0.1.1.dist-info/WHEEL
sumerian_ner-0.1.1.dist-info/entry_points.txt
sumerian_ner-0.1.1.dist-info/top_level.txt
