Metadata-Version: 2.1
Name: sumerian-ner
Version: 0.1.1
Summary: Sumerian Named Entity Recognition
Home-page: https://github.com/wwunlp/sner
Author: WWUNLP SNER Team
Author-email: UNKNOWN
License: UNKNOWN
Project-URL: Bug Reports, https://github.com/wwunlp/sner/issues
Project-URL: Source, https://github.com/wwunlp/sner
Platform: UNKNOWN
Requires-Dist: editdistance
Requires-Dist: matplotlib
Requires-Dist: numpy
Requires-Dist: pandas
Requires-Dist: scikit-learn
Requires-Dist: scipy
